MANIFEST.in
README.rst
setup.py
plaster_spring_boot.egg-info/PKG-INFO
plaster_spring_boot.egg-info/SOURCES.txt
plaster_spring_boot.egg-info/dependency_links.txt
plaster_spring_boot.egg-info/entry_points.txt
plaster_spring_boot.egg-info/requires.txt
plaster_spring_boot.egg-info/top_level.txt
src/__init__.py
src/plaster.py
src/converter/__init__.py
src/converter/controller.py
src/converter/model.py
src/converter/repository.py
src/converter/service.py
src/data/__init__.py
src/data/java_types.py
src/data/modes.py
src/data/regex.py
src/data/settings.py
src/data/strings.py
src/data/types.py
src/data/version.py
src/domain/__init__.py
src/domain/field.py
src/domain/file_information.py
src/domain/java_type.py
src/generation/__init__.py
src/generation/disposer.py
src/generation/generator.py
src/template/__init__.py
src/template/controller.py
src/template/repository.py
src/template/service.py
src/template/template_util.py
src/template/model/__init__.py
src/template/model/current.py
src/template/model/current_lombok.py
src/template/model/model.py
src/util/__init__.py
src/util/util.py
test/__init__.py
test/template/__init__.py
test/template/model/__init__.py
test/template/model/model_test.py