Metadata-Version: 1.1
Name: plaster-spring-boot
Version: 0.3.0
Summary: Generates scaffolding for new models for Spring Boot projects
Home-page: https://github.com/JDrost1818/plaster
Author: Jake Drost
Author-email: JDrost1818@gmail.com
License: MIT
Keywords: sample setuptools development
Platform: UNKNOWN
Classifier: Development Status :: 4 - Beta
Classifier: Intended Audience :: Developers
Classifier: Topic :: Software Development :: Code Generators
Classifier: License :: OSI Approved :: MIT License
Classifier: Programming Language :: Python :: 2
